Workbook
Name Sub: OFFSET(TabelaSistemas[[#Headers],[Subsistema]],MATCH(Ativos!$F1,TabelaSistemas[Sistema],0),0,COUNTIF(TabelaSistemas[Sistema],Ativos!$F1),1)

Sheet Dashboard
A1: MVP Manutenção Predial — Apartamento / Estudo de Caso
A3: Indicador | B3: Valor | D3: Custo por sistema | G3: Custo por ambiente
A4: Total de ativos cadastrados | B4: =COUNTA(Ativos!A2:A200) -> 14 | D4: Sistema | E4: Custo previsto | G4: Ambiente | H4: Custo previsto
A5: Custo total previsto | B5: =SUM(Ativos!R2:R200) -> 74750 | D5: Climatização | E5: =SUMIF(Ativos!E:E,D5,Ativos!R:R) -> 720 | G5: Suíte 1 | H5: =SUMIF(Ativos!C:C,G5,Ativos!R:R) -> 180
A6: Itens vencidos | B6: =COUNTIF(Ativos!U2:U200,"Vencido") -> 10 | D6: Drenagem | E6: =SUMIF(Ativos!E:E,D6,Ativos!R:R) -> 0 | G6: Banheiro suíte 1 | H6: =SUMIF(Ativos!C:C,G6,Ativos!R:R) -> 0
A7: Próximos 30 dias | B7: =COUNTIF(Ativos!U2:U200,"Próx. 30 dias") -> 0 | D7: Elétrico | E7: =SUMIF(Ativos!E:E,D7,Ativos!R:R) -> 20100 | G7: Suíte 2 | H7: =SUMIF(Ativos!C:C,G7,Ativos!R:R) -> 180
A8: Próximos 90 dias | B8: =COUNTIF(Ativos!U2:U200,"Próx. 90 dias") -> 0 | D8: Esgoto | E8: =SUMIF(Ativos!E:E,D8,Ativos!R:R) -> 80 | G8: Banheiro suíte 2 | H8: =SUMIF(Ativos!C:C,G8,Ativos!R:R) -> 380
D9: Esquadrias | E9: =SUMIF(Ativos!E:E,D9,Ativos!R:R) -> 120 | G9: Suíte 3 | H9: =SUMIF(Ativos!C:C,G9,Ativos!R:R) -> 180
B10: =SUM(B13:B18) -> 126840 | D10: Gás | E10: =SUMIF(Ativos!E:E,D10,Ativos!R:R) -> 180 | G10: Banheiro suíte 3 | H10: =SUMIF(Ativos!C:C,G10,Ativos!R:R) -> 0
A11: Custo por ano | D11: Hidráulico | E11: =SUMIF(Ativos!E:E,D11,Ativos!R:R) -> 300 | G11: Escritório 1 | H11: =SUMIF(Ativos!C:C,G11,Ativos!R:R) -> 100
A12: Ano | B12: Gasto previsto | D12: Iluminação | E12: =SUMIF(Ativos!E:E,D12,Ativos!R:R) -> 0 | G12: Escritório 2 | H12: =SUMIF(Ativos!C:C,G12,Ativos!R:R) -> 0
A13: 2025 | B13: {=SUMPRODUCT(Ativos!R1:R15,MMULT(--(IFERROR(YEAR(Ativos!Y1:BD15),0)=A13),TRANSPOSE(COLUMN(Ativos!Y1:BD15)^0)))} -> 22370 | D13: Marcenaria | E13: =SUMIF(Ativos!E:E,D13,Ativos!R:R) -> 150 | G13: Sala | H13: =SUMIF(Ativos!C:C,G13,Ativos!R:R) -> 22680
A14: 2026 | B14: {=SUMPRODUCT(Ativos!R2:R16,MMULT(--(IFERROR(YEAR(Ativos!Y2:BD16),0)=A14),TRANSPOSE(COLUMN(Ativos!Y2:BD16)^0)))} -> 2270 | D14: Pintura | E14: =SUMIF(Ativos!E:E,D14,Ativos!R:R) -> 2500 | G14: Varanda | H14: =SUMIF(Ativos!C:C,G14,Ativos!R:R) -> 720
A15: 2027 | B15: {=SUMPRODUCT(Ativos!R3:R17,MMULT(--(IFERROR(YEAR(Ativos!Y3:BD17),0)=A15),TRANSPOSE(COLUMN(Ativos!Y3:BD17)^0)))} -> 22820 | D15: Revestimentos | E15: =SUMIF(Ativos!E:E,D15,Ativos!R:R) -> 50600 | G15: Lavabo | H15: =SUMIF(Ativos!C:C,G15,Ativos!R:R) -> 0
A16: 2028 | B16: {=SUMPRODUCT(Ativos!R4:R18,MMULT(--(IFERROR(YEAR(Ativos!Y4:BD18),0)=A16),TRANSPOSE(COLUMN(Ativos!Y4:BD18)^0)))} -> 5260 | D16: Segurança/acesso | E16: =SUMIF(Ativos!E:E,D16,Ativos!R:R) -> 0 | G16: Copa/cozinha | H16: =SUMIF(Ativos!C:C,G16,Ativos!R:R) -> 330
A17: 2029 | B17: {=SUMPRODUCT(Ativos!R5:R19,MMULT(--(IFERROR(YEAR(Ativos!Y5:BD19),0)=A17),TRANSPOSE(COLUMN(Ativos!Y5:BD19)^0)))} -> 21990 | G17: Área de serviço | H17: =SUMIF(Ativos!C:C,G17,Ativos!R:R) -> 0
A18: 2030 | B18: {=SUMPRODUCT(Ativos!R6:R20,MMULT(--(IFERROR(YEAR(Ativos!Y6:BD20),0)=A18),TRANSPOSE(COLUMN(Ativos!Y6:BD20)^0)))} -> 52130 | G18: Suíte dependência | H18: =SUMIF(Ativos!C:C,G18,Ativos!R:R) -> 0
B19: criar gantt com custos | G19: Banheiro dependência | H19: =SUMIF(Ativos!C:C,G19,Ativos!R:R) -> 0
E21: total
A25: contribuicao por ano | C25: aporte mensal | D25: 1 | E25: =SUM(E27:E32) -> 126840 | F25: =SUM(F27:F32) -> 0
A26: valor mensal | B26: periodo | C26: acumulado futuro | D26: por condomino | E26: arrecadacao anual | F26: saldo
A27: =B13/12/B27 -> 1864.1667 | B27: =1+A13-$A$13 -> 1 | C27: =SUM(A27:A32) -> 3792.75 | D27: =C27/$D$25 -> 3792.75 | E27: =C27*12 -> 45513 | F27: =E27-B13 -> 23143
A28: =B14/12/B28 -> 94.583333 | B28: =1+A14-$A$13 -> 2 | C28: =SUM(A28:A32) -> 1928.5833 | D28: =C28/$D$25 -> 1928.5833 | E28: =C28*12 -> 23143 | F28: =E28-B14 -> 20873
A29: =B15/12/B29 -> 633.88889 | B29: =1+A15-$A$13 -> 3 | C29: =SUM(A29:A32) -> 1834 | D29: =C29/$D$25 -> 1834 | E29: =C29*12 -> 22008 | F29: =E29-B15 -> -812
A30: =B16/12/B30 -> 109.58333 | B30: =1+A16-$A$13 -> 4 | C30: =SUM(A30:A32) -> 1200.1111 | D30: =C30/$D$25 -> 1200.1111 | E30: =C30*12 -> 14401.333 | F30: =E30-B16 -> 9141.3333
A31: =B17/12/B31 -> 366.5 | B31: =1+A17-$A$13 -> 5 | C31: =SUM(A31:A33) -> 1090.5278 | D31: =C31/$D$25 -> 1090.5278 | E31: =C31*12 -> 13086.333 | F31: =E31-B17 -> -8903.6667
A32: =B18/12/B32 -> 724.02778 | B32: =1+A18-$A$13 -> 6 | C32: =SUM(A32:A34) -> 724.02778 | D32: =C32/$D$25 -> 724.02778 | E32: =C32*12 -> 8688.3333 | F32: =E32-B18 -> -43441.667
J34: Como usar esta planilha
J35: 1. Preencha a aba Ativos, uma linha por componente manutenível.
J36: 2. Cadastre novos cômodos em Ambientes e novas rotinas em Rotinas.
J37: 3. A Próxima_manut, Ano, Mês, Custo_total e Status são calculados automaticamente.
J38: 4. Use filtros/tabelas dinâmicas a partir de Ativos ou Cronograma.
J39: 5. Para o app futuro, esta aba Ativos já funciona como protótipo do banco de dados.

Sheet Planilha1
E7: criar gantt com custos
D9: soma: | E9: =SUM(E12:E17) -> 200000 | J9: total
D10: Custo por ano | F10: contribuicao por ano | H10: mensalidade condominio | I10: 20 | J10: =SUM(J12:J17) -> 200000 | K10: =SUM(K12:K17) -> 2.910383e-11
D11: Ano | E11: Custo previsto | F11: valor mensal | G11: periodo | H11: acumulado futuro | I11: por condomino | J11: arrecadacao anual | K11: saldo
D12: 2025 | E12: 0 | F12: =E12/12/(1+D12-D$12) -> 0 | G12: =1+D12-D$12 -> 1 | H12: =SUM(F12:F17) -> 5555.5556 | I12: =H12/$I$10 -> 277.77778 | J12: =H12*12 -> 66666.667 | K12: =J12-E12 -> 66666.667
D13: 2026 | E13: 0 | F13: =E13/12/(1+D13-D$12) -> 0 | G13: =1+D13-D$12 -> 2 | H13: =SUM(F13:F18) -> 5555.5556 | I13: =H13/$I$10 -> 277.77778 | J13: =H13*12 -> 66666.667 | K13: =J13-E13 -> 66666.667
D14: 2027 | E14: 200000 | F14: =E14/12/(1+D14-D$12) -> 5555.5556 | G14: =1+D14-D$12 -> 3 | H14: =SUM(F14:F19) -> 5555.5556 | I14: =H14/$I$10 -> 277.77778 | J14: =H14*12 -> 66666.667 | K14: =J14-E14 -> -133333.33
D15: 2028 | E15: 0 | F15: =E15/12/(1+D15-D$12) -> 0 | G15: =1+D15-D$12 -> 4 | H15: =SUM(F15:F20) -> 0 | I15: =H15/$I$10 -> 0 | J15: =H15*12 -> 0 | K15: =J15-E15 -> 0
D16: 2029 | E16: 0 | F16: =E16/12/(1+D16-D$12) -> 0 | G16: =1+D16-D$12 -> 5 | H16: =SUM(F16:F21) -> 0 | I16: =H16/$I$10 -> 0 | J16: =H16*12 -> 0 | K16: =J16-E16 -> 0
D17: 2030 | E17: =TabelaAtivos[[#This Row],[Custo_unitário_estimado]] -> 0 | F17: =E17/12/(1+D17-D$12) -> 0 | G17: =1+D17-D$12 -> 6 | H17: =SUM(F17:F22) -> 0 | I17: =H17/$I$10 -> 0 | J17: =H17*12 -> 0 | K17: =J17-E17 -> 0
D28: 46164 | E28: =EDATE(D28,E32) -> 46256 | F28: 46560 | H28: =_xleta.DATE -> #VALUE!
H29: =EDATE(D28,E33) -> 46287
E30: 31 | H30: {=_xlfn.SEQUENCE(1,E32,D28,F28)} -> 46164 | I30: 92724 | J30: 139284
D31: inicio | E31: periodo | F31: data final
E32: 3 | H32: {=DATA.MÊS(D28,_xlfn.SEQUENCE(10,1,0,F28))} -> #NAME?
E33: 4
E34: 365 | H34: {=_xlfn.SEQUENCE(1,E32,D28,F28)} -> 46164 | I34: 92724 | J34: 139284
E35: =(F28-D28)/E34 -> 1.0849315 | H35: {=_xlfn.SEQUENCE(ROUNDDOWN((F28-D28)/(E28-D28),0),1,D28,E28-D28)} -> 46164
D36: total vezes | E36: =ROUNDDOWN((F28-D28)/(E28-D28),0) -> 4 | G36: =H36-H35 -> 92 | H36: 46256
H37: 46348
H38: 46440

Sheet Ativos
A1: ID | B1: Cod_ambiente | C1: Ambiente | D1: Zona | E1: Sistema | F1: Subsistema | G1: Ativo | H1: Componente | I1: Ação_prevista | J1: Quantidade | K1: Unidade | L1: Periodicidade_meses | M1: Última_manut | N1: Próxima_manut | O1: Ano | P1: Mês | Q1: Custo_unitário_estimado | R1: Custo_total_estimado | S1: Prioridade | T1: Estado | U1: Status | V1: Responsável | W1: Observações | X1: ano encerramento | Z1: =COUNTIFS(Y2:AE16,">="&AA1,Y2:AE16,"<"&AB1) -> 17 | AA1: 45658 | AB1: 46023
A2: HID-S2B-001 | B2: =_xlfn.XLOOKUP(TabelaAtivos[[#This Row],[Ambiente]],TabelaAmbientes[Ambiente],TabelaAmbientes[Cod_ambiente],"",0,1) -> S2B | C2: Banheiro suíte 2 | D2: =_xlfn.XLOOKUP(TabelaAtivos[[#This Row],[Ambiente]],TabelaAmbientes[Ambiente],TabelaAmbientes[Zona],"",0,1) -> Área íntima | E2: Hidráulico | F2: Água fria | G2: Lavatório | H2: Torneira | I2: Inspeção / troca de reparo | J2: 1 | K2: un | L2: 12 | M2: 45667 | N2: =IF(M2="","",EDATE(M2,L2)) -> 46032 | O2: =IF(N2="","",YEAR(N2)) -> 2026 | P2: =IF(N2="","",TEXT(N2,"mmm")) -> jan | Q2: 150 | R2: =IF(OR(J2="",Q2=""),"",J2*Q2) -> 150 | S2: Média | T2: Bom | U2: =IF(N2="","Sem data",IF(N2<TODAY(),"Vencido",IF(N2<=TODAY()+30,"Próx. 30 dias",IF(N2<=TODAY()+90,"Próx. 90 dias","Programado")))) -> Vencido | V2: Encanador | W2: Exemplo: verificar gotejamento eventual | X2: 51482 | Y2: {=_xlfn.SEQUENCE(1,ROUNDDOWN((TabelaAtivos[[#This Row],[ano encerramento]]-TabelaAtivos[[#This Row],[Última_manut]])/(TabelaAtivos[[#This Row],[Próxima_manut]]-TabelaAtivos[[#This Row],[Última_manut]]),0),TabelaAtivos[[#This Row],[Última_manut]],TabelaAtivos[[#This Row],[Próxima_manut]]-TabelaAtivos[[#This Row],[Última_manut]])} -> 45667 | Z2: 46032 | AA2: 46397 | AB2: 46762 | AC2: 47127 | AD2: 47492 | AE2: 47857 | AF2: 48222 | AG2: 48587 | AH2: 48952 | AI2: 49317 | AJ2: 49682 | AK2: 50047 | AL2: 50412 | AM2: 50777
A3: ESG-S2B-001 | B3: =_xlfn.XLOOKUP(TabelaAtivos[[#This Row],[Ambiente]],TabelaAmbientes[Ambiente],TabelaAmbientes[Cod_ambiente],"",0,1) -> S2B | C3: Banheiro suíte 2 | D3: =_xlfn.XLOOKUP(TabelaAtivos[[#This Row],[Ambiente]],TabelaAmbientes[Ambiente],TabelaAmbientes[Zona],"",0,1) -> Área íntima | E3: Esgoto | F3: Esgoto sanitário | G3: Lavatório | H3: Sifão | I3: Limpeza / inspeção | J3: 1 | K3: un | L3: 12 | M3: 45667 | N3: =IF(M3="","",EDATE(M3,L3)) -> 46032 | O3: =IF(N3="","",YEAR(N3)) -> 2026 | P3: =IF(N3="","",TEXT(N3,"mmm")) -> jan | Q3: 80 | R3: =IF(OR(J3="",Q3=""),"",J3*Q3) -> 80 | S3: Baixa | T3: Bom | U3: =IF(N3="","Sem data",IF(N3<TODAY(),"Vencido",IF(N3<=TODAY()+30,"Próx. 30 dias",IF(N3<=TODAY()+90,"Próx. 90 dias","Programado")))) -> Vencido | V3: Encanador | X3: 51482 | Y3: {=_xlfn.SEQUENCE(1,ROUNDDOWN((TabelaAtivos[[#This Row],[ano encerramento]]-TabelaAtivos[[#This Row],[Última_manut]])/(TabelaAtivos[[#This Row],[Próxima_manut]]-TabelaAtivos[[#This Row],[Última_manut]]),0),TabelaAtivos[[#This Row],[Última_manut]],TabelaAtivos[[#This Row],[Próxima_manut]]-TabelaAtivos[[#This Row],[Última_manut]])} -> 45667 | Z3: 46032 | AA3: 46397 | AB3: 46762 | AC3: 47127 | AD3: 47492 | AE3: 47857 | AF3: 48222 | AG3: 48587 | AH3: 48952 | AI3: 49317 | AJ3: 49682 | AK3: 50047 | AL3: 50412 | AM3: 50777
A4: HID-S2B-002 | B4: =_xlfn.XLOOKUP(TabelaAtivos[[#This Row],[Ambiente]],TabelaAmbientes[Ambiente],TabelaAmbientes[Cod_ambiente],"",0,1) -> S2B | C4: Banheiro suíte 2 | D4: =_xlfn.XLOOKUP(TabelaAtivos[[#This Row],[Ambiente]],TabelaAmbientes[Ambiente],TabelaAmbientes[Zona],"",0,1) -> Área íntima | E4: Hidráulico | F4: Água fria | G4: Bacia sanitária | H4: Caixa acoplada / válvula | I4: Inspeção / regulagem | J4: 1 | K4: un | L4: 12 | M4: 45667 | N4: =IF(M4="","",EDATE(M4,L4)) -> 46032 | O4: =IF(N4="","",YEAR(N4)) -> 2026 | P4: =IF(N4="","",TEXT(N4,"mmm")) -> jan | Q4: 150 | R4: =IF(OR(J4="",Q4=""),"",J4*Q4) -> 150 | S4: Média | T4: Bom | U4: =IF(N4="","Sem data",IF(N4<TODAY(),"Vencido",IF(N4<=TODAY()+30,"Próx. 30 dias",IF(N4<=TODAY()+90,"Próx. 90 dias","Programado")))) -> Vencido | V4: Encanador | X4: 51482 | Y4: {=_xlfn.SEQUENCE(1,ROUNDDOWN((TabelaAtivos[[#This Row],[ano encerramento]]-TabelaAtivos[[#This Row],[Última_manut]])/(TabelaAtivos[[#This Row],[Próxima_manut]]-TabelaAtivos[[#This Row],[Última_manut]]),0),TabelaAtivos[[#This Row],[Última_manut]],TabelaAtivos[[#This Row],[Próxima_manut]]-TabelaAtivos[[#This Row],[Última_manut]])} -> 45667 | Z4: 46032 | AA4: 46397 | AB4: 46762 | AC4: 47127 | AD4: 47492 | AE4: 47857 | AF4: 48222 | AG4: 48587 | AH4: 48952 | AI4: 49317 | AJ4: 49682 | AK4: 50047 | AL4: 50412 | AM4: 50777
A5: CLI-SALA-001 | B5: =_xlfn.XLOOKUP(TabelaAtivos[[#This Row],[Ambiente]],TabelaAmbientes[Ambiente],TabelaAmbientes[Cod_ambiente],"",0,1) -> SALA | C5: Sala | D5: =_xlfn.XLOOKUP(TabelaAtivos[[#This Row],[Ambiente]],TabelaAmbientes[Ambiente],TabelaAmbientes[Zona],"",0,1) -> Social | E5: Climatização | F5: Split | G5: Ar-condicionado | H5: Evaporadora / condensadora | I5: Limpeza preventiva | J5: 1 | K5: un | L5: 6 | M5: 45667 | N5: =IF(M5="","",EDATE(M5,L5)) -> 45848 | O5: =IF(N5="","",YEAR(N5)) -> 2025 | P5: =IF(N5="","",TEXT(N5,"mmm")) -> jul | Q5: 180 | R5: =IF(OR(J5="",Q5=""),"",J5*Q5) -> 180 | S5: Alta | T5: Regular | U5: =IF(N5="","Sem data",IF(N5<TODAY(),"Vencido",IF(N5<=TODAY()+30,"Próx. 30 dias",IF(N5<=TODAY()+90,"Próx. 90 dias","Programado")))) -> Vencido | V5: Técnico de ar-condicionado | X5: 51482 | Y5: {=_xlfn.SEQUENCE(1,ROUNDDOWN((TabelaAtivos[[#This Row],[ano encerramento]]-TabelaAtivos[[#This Row],[Última_manut]])/(TabelaAtivos[[#This Row],[Próxima_manut]]-TabelaAtivos[[#This Row],[Última_manut]]),0),TabelaAtivos[[#This Row],[Última_manut]],TabelaAtivos[[#This Row],[Próxima_manut]]-TabelaAtivos[[#This Row],[Última_manut]])} -> 45667 | Z5: 45848 | AA5: 46029 | AB5: 46210 | AC5: 46391 | AD5: 46572 | AE5: 46753 | AF5: 46934 | AG5: 47115 | AH5: 47296 | AI5: 47477 | AJ5: 47658 | AK5: 47839 | AL5: 48020 | AM5: 48201 | AN5: 48382 | AO5: 48563 | AP5: 48744 | AQ5: 48925 | AR5: 49106 | AS5: 49287 | AT5: 49468 | AU5: 49649 | AV5: 49830 | AW5: 50011 | AX5: 50192 | AY5: 50373 | AZ5: 50554 | BA5: 50735 | BB5: 50916 | BC5: 51097 | BD5: 51278
A6: CLI-S1-001 | B6: =_xlfn.XLOOKUP(TabelaAtivos[[#This Row],[Ambiente]],TabelaAmbientes[Ambiente],TabelaAmbientes[Cod_ambiente],"",0,1) -> S1 | C6: Suíte 1 | D6: =_xlfn.XLOOKUP(TabelaAtivos[[#This Row],[Ambiente]],TabelaAmbientes[Ambiente],TabelaAmbientes[Zona],"",0,1) -> Área íntima | E6: Climatização | F6: Split | G6: Ar-condicionado | H6: Evaporadora / condensadora | I6: Limpeza preventiva | J6: 1 | K6: un | L6: 6 | M6: 45667 | N6: =IF(M6="","",EDATE(M6,L6)) -> 45848 | O6: =IF(N6="","",YEAR(N6)) -> 2025 | P6: =IF(N6="","",TEXT(N6,"mmm")) -> jul | Q6: 180 | R6: =IF(OR(J6="",Q6=""),"",J6*Q6) -> 180 | S6: Alta | T6: Bom | U6: =IF(N6="","Sem data",IF(N6<TODAY(),"Vencido",IF(N6<=TODAY()+30,"Próx. 30 dias",IF(N6<=TODAY()+90,"Próx. 90 dias","Programado")))) -> Vencido | V6: Técnico de ar-condicionado | X6: 51482 | Y6: {=_xlfn.SEQUENCE(1,ROUNDDOWN((TabelaAtivos[[#This Row],[ano encerramento]]-TabelaAtivos[[#This Row],[Última_manut]])/(TabelaAtivos[[#This Row],[Próxima_manut]]-TabelaAtivos[[#This Row],[Última_manut]]),0),TabelaAtivos[[#This Row],[Última_manut]],TabelaAtivos[[#This Row],[Próxima_manut]]-TabelaAtivos[[#This Row],[Última_manut]])} -> 45667 | Z6: 45848 | AA6: 46029 | AB6: 46210 | AC6: 46391 | AD6: 46572 | AE6: 46753 | AF6: 46934 | AG6: 47115 | AH6: 47296 | AI6: 47477 | AJ6: 47658 | AK6: 47839 | AL6: 48020 | AM6: 48201 | AN6: 48382 | AO6: 48563 | AP6: 48744 | AQ6: 48925 | AR6: 49106 | AS6: 49287 | AT6: 49468 | AU6: 49649 | AV6: 49830 | AW6: 50011 | AX6: 50192 | AY6: 50373 | AZ6: 50554 | BA6: 50735 | BB6: 50916 | BC6: 51097 | BD6: 51278
A7: CLI-S2-001 | B7: =_xlfn.XLOOKUP(TabelaAtivos[[#This Row],[Ambiente]],TabelaAmbientes[Ambiente],TabelaAmbientes[Cod_ambiente],"",0,1) -> S2 | C7: Suíte 2 | D7: =_xlfn.XLOOKUP(TabelaAtivos[[#This Row],[Ambiente]],TabelaAmbientes[Ambiente],TabelaAmbientes[Zona],"",0,1) -> Área íntima | E7: Climatização | F7: Split | G7: Ar-condicionado | H7: Evaporadora / condensadora | I7: Limpeza preventiva | J7: 1 | K7: un | L7: 6 | M7: 45667 | N7: =IF(M7="","",EDATE(M7,L7)) -> 45848 | O7: =IF(N7="","",YEAR(N7)) -> 2025 | P7: =IF(N7="","",TEXT(N7,"mmm")) -> jul | Q7: 180 | R7: =IF(OR(J7="",Q7=""),"",J7*Q7) -> 180 | S7: Alta | T7: Bom | U7: =IF(N7="","Sem data",IF(N7<TODAY(),"Vencido",IF(N7<=TODAY()+30,"Próx. 30 dias",IF(N7<=TODAY()+90,"Próx. 90 dias","Programado")))) -> Vencido | V7: Técnico de ar-condicionado | X7: 51482 | Y7: {=_xlfn.SEQUENCE(1,ROUNDDOWN((TabelaAtivos[[#This Row],[ano encerramento]]-TabelaAtivos[[#This Row],[Última_manut]])/(TabelaAtivos[[#This Row],[Próxima_manut]]-TabelaAtivos[[#This Row],[Última_manut]]),0),TabelaAtivos[[#This Row],[Última_manut]],TabelaAtivos[[#This Row],[Próxima_manut]]-TabelaAtivos[[#This Row],[Última_manut]])} -> 45667 | Z7: 45848 | AA7: 46029 | AB7: 46210 | AC7: 46391 | AD7: 46572 | AE7: 46753 | AF7: 46934 | AG7: 47115 | AH7: 47296 | AI7: 47477 | AJ7: 47658 | AK7: 47839 | AL7: 48020 | AM7: 48201 | AN7: 48382 | AO7: 48563 | AP7: 48744 | AQ7: 48925 | AR7: 49106 | AS7: 49287 | AT7: 49468 | AU7: 49649 | AV7: 49830 | AW7: 50011 | AX7: 50192 | AY7: 50373 | AZ7: 50554 | BA7: 50735 | BB7: 50916 | BC7: 51097 | BD7: 51278
A8: CLI-S3-001 | B8: =_xlfn.XLOOKUP(TabelaAtivos[[#This Row],[Ambiente]],TabelaAmbientes[Ambiente],TabelaAmbientes[Cod_ambiente],"",0,1) -> S3 | C8: Suíte 3 | D8: =_xlfn.XLOOKUP(TabelaAtivos[[#This Row],[Ambiente]],TabelaAmbientes[Ambiente],TabelaAmbientes[Zona],"",0,1) -> Área íntima | E8: Climatização | F8: Split | G8: Ar-condicionado | H8: Evaporadora / condensadora | I8: Limpeza preventiva | J8: 1 | K8: un | L8: 6 | M8: 45667 | N8: =IF(M8="","",EDATE(M8,L8)) -> 45848 | O8: =IF(N8="","",YEAR(N8)) -> 2025 | P8: =IF(N8="","",TEXT(N8,"mmm")) -> jul | Q8: 180 | R8: =IF(OR(J8="",Q8=""),"",J8*Q8) -> 180 | S8: Alta | T8: Bom | U8: =IF(N8="","Sem data",IF(N8<TODAY(),"Vencido",IF(N8<=TODAY()+30,"Próx. 30 dias",IF(N8<=TODAY()+90,"Próx. 90 dias","Programado")))) -> Vencido | V8: Técnico de ar-condicionado | X8: 51482 | Y8: {=_xlfn.SEQUENCE(1,ROUNDDOWN((TabelaAtivos[[#This Row],[ano encerramento]]-TabelaAtivos[[#This Row],[Última_manut]])/(TabelaAtivos[[#This Row],[Próxima_manut]]-TabelaAtivos[[#This Row],[Última_manut]]),0),TabelaAtivos[[#This Row],[Última_manut]],TabelaAtivos[[#This Row],[Próxima_manut]]-TabelaAtivos[[#This Row],[Última_manut]])} -> 45667 | Z8: 45848 | AA8: 46029 | AB8: 46210 | AC8: 46391 | AD8: 46572 | AE8: 46753 | AF8: 46934 | AG8: 47115 | AH8: 47296 | AI8: 47477 | AJ8: 47658 | AK8: 47839 | AL8: 48020 | AM8: 48201 | AN8: 48382 | AO8: 48563 | AP8: 48744 | AQ8: 48925 | AR8: 49106 | AS8: 49287 | AT8: 49468 | AU8: 49649 | AV8: 49830 | AW8: 50011 | AX8: 50192 | AY8: 50373 | AZ8: 50554 | BA8: 50735 | BB8: 50916 | BC8: 51097 | BD8: 51278
A9: ELE-APT-001 | B9: =_xlfn.XLOOKUP(TabelaAtivos[[#This Row],[Ambiente]],TabelaAmbientes[Ambiente],TabelaAmbientes[Cod_ambiente],"",0,1) -> SALA | C9: Sala | D9: =_xlfn.XLOOKUP(TabelaAtivos[[#This Row],[Ambiente]],TabelaAmbientes[Ambiente],TabelaAmbientes[Zona],"",0,1) -> Social | E9: Elétrico | F9: Quadro | G9: Quadro elétrico | H9: Disjuntores | I9: Inspeção | J9: 1 | K9: un | L9: 24 | M9: 45667 | N9: =IF(M9="","",EDATE(M9,L9)) -> 46397 | O9: =IF(N9="","",YEAR(N9)) -> 2027 | P9: =IF(N9="","",TEXT(N9,"mmm")) -> jan | Q9: 20000 | R9: =IF(OR(J9="",Q9=""),"",J9*Q9) -> 20000 | S9: Média | T9: Bom | U9: =IF(N9="","Sem data",IF(N9<TODAY(),"Vencido",IF(N9<=TODAY()+30,"Próx. 30 dias",IF(N9<=TODAY()+90,"Próx. 90 dias","Programado")))) -> Programado | V9: Eletricista | W9: Representa quadro geral do apartamento | X9: 51482 | Y9: {=_xlfn.SEQUENCE(1,ROUNDDOWN((TabelaAtivos[[#This Row],[ano encerramento]]-TabelaAtivos[[#This Row],[Última_manut]])/(TabelaAtivos[[#This Row],[Próxima_manut]]-TabelaAtivos[[#This Row],[Última_manut]]),0),TabelaAtivos[[#This Row],[Última_manut]],TabelaAtivos[[#This Row],[Próxima_manut]]-TabelaAtivos[[#This Row],[Última_manut]])} -> 45667 | Z9: 46397 | AA9: 47127 | AB9: 47857 | AC9: 48587 | AD9: 49317 | AE9: 50047
A10: ELE-ESC1-001 | B10: =_xlfn.XLOOKUP(TabelaAtivos[[#This Row],[Ambiente]],TabelaAmbientes[Ambiente],TabelaAmbientes[Cod_ambiente],"",0,1) -> ESC1 | C10: Escritório 1 | D10: =_xlfn.XLOOKUP(TabelaAtivos[[#This Row],[Ambiente]],TabelaAmbientes[Ambiente],TabelaAmbientes[Zona],"",0,1) -> Trabalho | E10: Elétrico | F10: Tomadas | G10: Tomadas gerais | H10: Conjunto de tomadas | I10: Inspeção | J10: 1 | K10: cj | L10: 24 | M10: 45667 | N10: =IF(M10="","",EDATE(M10,L10)) -> 46397 | O10: =IF(N10="","",YEAR(N10)) -> 2027 | P10: =IF(N10="","",TEXT(N10,"mmm")) -> jan | Q10: 100 | R10: =IF(OR(J10="",Q10=""),"",J10*Q10) -> 100 | S10: Baixa | T10: Bom | U10: =IF(N10="","Sem data",IF(N10<TODAY(),"Vencido",IF(N10<=TODAY()+30,"Próx. 30 dias",IF(N10<=TODAY()+90,"Próx. 90 dias","Programado")))) -> Programado | V10: Eletricista | X10: 51482 | Y10: {=_xlfn.SEQUENCE(1,ROUNDDOWN((TabelaAtivos[[#This Row],[ano encerramento]]-TabelaAtivos[[#This Row],[Última_manut]])/(TabelaAtivos[[#This Row],[Próxima_manut]]-TabelaAtivos[[#This Row],[Última_manut]]),0),TabelaAtivos[[#This Row],[Última_manut]],TabelaAtivos[[#This Row],[Próxima_manut]]-TabelaAtivos[[#This Row],[Última_manut]])} -> 45667 | Z10: 46397 | AA10: 47127 | AB10: 47857 | AC10: 48587 | AD10: 49317 | AE10: 50047
A11: GAS-COPA-001 | B11: =_xlfn.XLOOKUP(TabelaAtivos[[#This Row],[Ambiente]],TabelaAmbientes[Ambiente],TabelaAmbientes[Cod_ambiente],"",0,1) -> COPA | C11: Copa/cozinha | D11: =_xlfn.XLOOKUP(TabelaAtivos[[#This Row],[Ambiente]],TabelaAmbientes[Ambiente],TabelaAmbientes[Zona],"",0,1) -> Serviço | E11: Gás | F11: Tubulação/ponto | G11: Ponto de gás | H11: Mangueira / registro | I11: Inspeção / troca preventiva | J11: 1 | K11: un | L11: 12 | M11: 45667 | N11: =IF(M11="","",EDATE(M11,L11)) -> 46032 | O11: =IF(N11="","",YEAR(N11)) -> 2026 | P11: =IF(N11="","",TEXT(N11,"mmm")) -> jan | Q11: 180 | R11: =IF(OR(J11="",Q11=""),"",J11*Q11) -> 180 | S11: Alta | T11: Bom | U11: =IF(N11="","Sem data",IF(N11<TODAY(),"Vencido",IF(N11<=TODAY()+30,"Próx. 30 dias",IF(N11<=TODAY()+90,"Próx. 90 dias","Programado")))) -> Vencido | V11: Técnico de gás | X11: 51482 | Y11: {=_xlfn.SEQUENCE(1,ROUNDDOWN((TabelaAtivos[[#This Row],[ano encerramento]]-TabelaAtivos[[#This Row],[Última_manut]])/(TabelaAtivos[[#This Row],[Próxima_manut]]-TabelaAtivos[[#This Row],[Última_manut]]),0),TabelaAtivos[[#This Row],[Última_manut]],TabelaAtivos[[#This Row],[Próxima_manut]]-TabelaAtivos[[#This Row],[Última_manut]])} -> 45667 | Z11: 46032 | AA11: 46397 | AB11: 46762 | AC11: 47127 | AD11: 47492 | AE11: 47857 | AF11: 48222 | AG11: 48587 | AH11: 48952 | AI11: 49317 | AJ11: 49682 | AK11: 50047 | AL11: 50412 | AM11: 50777
A12: PIN-SALA-001 | B12: =_xlfn.XLOOKUP(TabelaAtivos[[#This Row],[Ambiente]],TabelaAmbientes[Ambiente],TabelaAmbientes[Cod_ambiente],"",0,1) -> SALA | C12: Sala | D12: =_xlfn.XLOOKUP(TabelaAtivos[[#This Row],[Ambiente]],TabelaAmbientes[Ambiente],TabelaAmbientes[Zona],"",0,1) -> Social | E12: Pintura | F12: Interna | G12: Paredes internas | H12: Pintura | I12: Repintura | J12: 1 | K12: serv | L12: 48 | M12: 45301 | N12: =IF(M12="","",EDATE(M12,L12)) -> 46762 | O12: =IF(N12="","",YEAR(N12)) -> 2028 | P12: =IF(N12="","",TEXT(N12,"mmm")) -> jan | Q12: 2500 | R12: =IF(OR(J12="",Q12=""),"",J12*Q12) -> 2500 | S12: Média | T12: Bom | U12: =IF(N12="","Sem data",IF(N12<TODAY(),"Vencido",IF(N12<=TODAY()+30,"Próx. 30 dias",IF(N12<=TODAY()+90,"Próx. 90 dias","Programado")))) -> Programado | V12: Pintor | W12: Valor exemplo para sala | X12: 51482 | Y12: {=_xlfn.SEQUENCE(1,ROUNDDOWN((TabelaAtivos[[#This Row],[ano encerramento]]-TabelaAtivos[[#This Row],[Última_manut]])/(TabelaAtivos[[#This Row],[Próxima_manut]]-TabelaAtivos[[#This Row],[Última_manut]]),0),TabelaAtivos[[#This Row],[Última_manut]],TabelaAtivos[[#This Row],[Próxima_manut]]-TabelaAtivos[[#This Row],[Última_manut]])} -> 45301 | Z12: 46762 | AA12: 48223 | AB12: 49684
A13: REV-VAR-001 | B13: =_xlfn.XLOOKUP(TabelaAtivos[[#This Row],[Ambiente]],TabelaAmbientes[Ambiente],TabelaAmbientes[Cod_ambiente],"",0,1) -> VAR | C13: Varanda | D13: =_xlfn.XLOOKUP(TabelaAtivos[[#This Row],[Ambiente]],TabelaAmbientes[Ambiente],TabelaAmbientes[Zona],"",0,1) -> Social | E13: Revestimentos | F13: Piso | G13: Piso | H13: Rejunte | I13: Inspeção / recomposição | J13: 1 | K13: serv | L13: 36 | M13: 45301 | N13: =IF(M13="","",EDATE(M13,L13)) -> 46397 | O13: =IF(N13="","",YEAR(N13)) -> 2027 | P13: =IF(N13="","",TEXT(N13,"mmm")) -> jan | Q13: 600 | R13: =IF(OR(J13="",Q13=""),"",J13*Q13) -> 600 | S13: Média | T13: Bom | U13: =IF(N13="","Sem data",IF(N13<TODAY(),"Vencido",IF(N13<=TODAY()+30,"Próx. 30 dias",IF(N13<=TODAY()+90,"Próx. 90 dias","Programado")))) -> Programado | V13: Pedreiro | X13: 51482 | Y13: {=_xlfn.SEQUENCE(1,ROUNDDOWN((TabelaAtivos[[#This Row],[ano encerramento]]-TabelaAtivos[[#This Row],[Última_manut]])/(TabelaAtivos[[#This Row],[Próxima_manut]]-TabelaAtivos[[#This Row],[Última_manut]]),0),TabelaAtivos[[#This Row],[Última_manut]],TabelaAtivos[[#This Row],[Próxima_manut]]-TabelaAtivos[[#This Row],[Última_manut]])} -> 45301 | Z13: 46397 | AA13: 47493 | AB13: 48589 | AC13: 49685
A14: ESQ-VAR-001 | B14: =_xlfn.XLOOKUP(TabelaAtivos[[#This Row],[Ambiente]],TabelaAmbientes[Ambiente],TabelaAmbientes[Cod_ambiente],"",0,1) -> VAR | C14: Varanda | D14: =_xlfn.XLOOKUP(TabelaAtivos[[#This Row],[Ambiente]],TabelaAmbientes[Ambiente],TabelaAmbientes[Zona],"",0,1) -> Social | E14: Esquadrias | F14: Janelas | G14: Esquadria da varanda | H14: Trilhos / roldanas | I14: Limpeza / regulagem | J14: 1 | K14: un | L14: 12 | M14: 45667 | N14: =IF(M14="","",EDATE(M14,L14)) -> 46032 | O14: =IF(N14="","",YEAR(N14)) -> 2026 | P14: =IF(N14="","",TEXT(N14,"mmm")) -> jan | Q14: 120 | R14: =IF(OR(J14="",Q14=""),"",J14*Q14) -> 120 | S14: Média | T14: Regular | U14: =IF(N14="","Sem data",IF(N14<TODAY(),"Vencido",IF(N14<=TODAY()+30,"Próx. 30 dias",IF(N14<=TODAY()+90,"Próx. 90 dias","Programado")))) -> Vencido | V14: Serralheiro | X14: 51482 | Y14: {=_xlfn.SEQUENCE(1,ROUNDDOWN((TabelaAtivos[[#This Row],[ano encerramento]]-TabelaAtivos[[#This Row],[Última_manut]])/(TabelaAtivos[[#This Row],[Próxima_manut]]-TabelaAtivos[[#This Row],[Última_manut]]),0),TabelaAtivos[[#This Row],[Última_manut]],TabelaAtivos[[#This Row],[Próxima_manut]]-TabelaAtivos[[#This Row],[Última_manut]])} -> 45667 | Z14: 46032 | AA14: 46397 | AB14: 46762 | AC14: 47127 | AD14: 47492 | AE14: 47857 | AF14: 48222 | AG14: 48587 | AH14: 48952 | AI14: 49317 | AJ14: 49682 | AK14: 50047 | AL14: 50412 | AM14: 50777
A15: MAR-COPA-001 | B15: =_xlfn.XLOOKUP(TabelaAtivos[[#This Row],[Ambiente]],TabelaAmbientes[Ambiente],TabelaAmbientes[Cod_ambiente],"",0,1) -> COPA | C15: Copa/cozinha | D15: =_xlfn.XLOOKUP(TabelaAtivos[[#This Row],[Ambiente]],TabelaAmbientes[Ambiente],TabelaAmbientes[Zona],"",0,1) -> Serviço | E15: Marcenaria | F15: Armários | G15: Armários da cozinha | H15: Dobradiças / corrediças | I15: Regulagem | J15: 1 | K15: serv | L15: 12 | M15: 45667 | N15: =IF(M15="","",EDATE(M15,L15)) -> 46032 | O15: =IF(N15="","",YEAR(N15)) -> 2026 | P15: =IF(N15="","",TEXT(N15,"mmm")) -> jan | Q15: 150 | R15: =IF(OR(J15="",Q15=""),"",J15*Q15) -> 150 | S15: Baixa | T15: Bom | U15: =IF(N15="","Sem data",IF(N15<TODAY(),"Vencido",IF(N15<=TODAY()+30,"Próx. 30 dias",IF(N15<=TODAY()+90,"Próx. 90 dias","Programado")))) -> Vencido | V15: Marceneiro | X15: 51482 | Y15: {=_xlfn.SEQUENCE(1,ROUNDDOWN((TabelaAtivos[[#This Row],[ano encerramento]]-TabelaAtivos[[#This Row],[Última_manut]])/(TabelaAtivos[[#This Row],[Próxima_manut]]-TabelaAtivos[[#This Row],[Última_manut]]),0),TabelaAtivos[[#This Row],[Última_manut]],TabelaAtivos[[#This Row],[Próxima_manut]]-TabelaAtivos[[#This Row],[Última_manut]])} -> 45667 | Z15: 46032 | AA15: 46397 | AB15: 46762 | AC15: 47127 | AD15: 47492 | AE15: 47857 | AF15: 48222 | AG15: 48587 | AH15: 48952 | AI15: 49317 | AJ15: 49682 | AK15: 50047 | AL15: 50412 | AM15: 50777
B16: =_xlfn.XLOOKUP(TabelaAtivos[[#This Row],[Ambiente]],TabelaAmbientes[Ambiente],TabelaAmbientes[Cod_ambiente],"",0,1) -> EXT | C16: Externo | D16: =_xlfn.XLOOKUP(TabelaAtivos[[#This Row],[Ambiente]],TabelaAmbientes[Ambiente],TabelaAmbientes[Zona],"",0,1) -> publica | E16: Revestimentos | G16: fachada | J16: 1 | L16: 60 | M16: 45667 | N16: =IF(M16="","",EDATE(M16,L16)) -> 47493 | O16: =IF(N16="","",YEAR(N16)) -> 2030 | P16: =IF(N16="","",TEXT(N16,"mmm")) -> jan | Q16: 50000 | R16: =IF(OR(J16="",Q16=""),"",J16*Q16) -> 50000 | U16: =IF(N16="","Sem data",IF(N16<TODAY(),"Vencido",IF(N16<=TODAY()+30,"Próx. 30 dias",IF(N16<=TODAY()+90,"Próx. 90 dias","Programado")))) -> Programado | X16: 51482 | Y16: {=_xlfn.SEQUENCE(1,ROUNDDOWN((TabelaAtivos[[#This Row],[ano encerramento]]-TabelaAtivos[[#This Row],[Última_manut]])/(TabelaAtivos[[#This Row],[Próxima_manut]]-TabelaAtivos[[#This Row],[Última_manut]]),0),TabelaAtivos[[#This Row],[Última_manut]],TabelaAtivos[[#This Row],[Próxima_manut]]-TabelaAtivos[[#This Row],[Última_manut]])} -> 45667 | Z16: 47493 | AA16: 49319
B17: =_xlfn.XLOOKUP(TabelaAtivos[[#This Row],[Ambiente]],TabelaAmbientes[Ambiente],TabelaAmbientes[Cod_ambiente],"",0,1) | O17: =IF(N17="","",YEAR(N17)) | P17: =IF(N17="","",TEXT(N17,"mmm")) | R17: =IF(OR(J17="",Q17=""),"",J17*Q17) | U17: =IF(N17="","Sem data",IF(N17<TODAY(),"Vencido",IF(N17<=TODAY()+30,"Próx. 30 dias",IF(N17<=TODAY()+90,"Próx. 90 dias","Programado")))) -> Sem data | X17: 51482
B18: =_xlfn.XLOOKUP(TabelaAtivos[[#This Row],[Ambiente]],TabelaAmbientes[Ambiente],TabelaAmbientes[Cod_ambiente],"",0,1) | D18: =_xlfn.XLOOKUP(TabelaAtivos[[#This Row],[Ambiente]],TabelaAmbientes[Ambiente],TabelaAmbientes[Zona],"",0,1) | N18: =IF(M18="","",EDATE(M18,L18)) | O18: =IF(N18="","",YEAR(N18)) | P18: =IF(N18="","",TEXT(N18,"mmm")) | R18: =IF(OR(J18="",Q18=""),"",J18*Q18) | U18: =IF(N18="","Sem data",IF(N18<TODAY(),"Vencido",IF(N18<=TODAY()+30,"Próx. 30 dias",IF(N18<=TODAY()+90,"Próx. 90 dias","Programado")))) -> Sem data | X18: 51482 | Y18: 13 | Z18: 17
B19: =_xlfn.XLOOKUP(TabelaAtivos[[#This Row],[Ambiente]],TabelaAmbientes[Ambiente],TabelaAmbientes[Cod_ambiente],"",0,1) | D19: =_xlfn.XLOOKUP(TabelaAtivos[[#This Row],[Ambiente]],TabelaAmbientes[Ambiente],TabelaAmbientes[Zona],"",0,1) | N19: =IF(M19="","",EDATE(M19,L19)) | O19: =IF(N19="","",YEAR(N19)) | P19: =IF(N19="","",TEXT(N19,"mmm")) | R19: =IF(OR(J19="",Q19=""),"",J19*Q19) | U19: =IF(N19="","Sem data",IF(N19<TODAY(),"Vencido",IF(N19<=TODAY()+30,"Próx. 30 dias",IF(N19<=TODAY()+90,"Próx. 90 dias","Programado")))) -> Sem data | X19: 51482
B20: =_xlfn.XLOOKUP(TabelaAtivos[[#This Row],[Ambiente]],TabelaAmbientes[Ambiente],TabelaAmbientes[Cod_ambiente],"",0,1) -> DEP | C20: Suíte dependência | D20: =_xlfn.XLOOKUP(TabelaAtivos[[#This Row],[Ambiente]],TabelaAmbientes[Ambiente],TabelaAmbientes[Zona],"",0,1) -> Serviço | N20: =IF(M20="","",EDATE(M20,L20)) | O20: =IF(N20="","",YEAR(N20)) | P20: =IF(N20="","",TEXT(N20,"mmm")) | R20: =IF(OR(J20="",Q20=""),"",J20*Q20) | U20: =IF(N20="","Sem data",IF(N20<TODAY(),"Vencido",IF(N20<=TODAY()+30,"Próx. 30 dias",IF(N20<=TODAY()+90,"Próx. 90 dias","Programado")))) -> Sem data | X20: 51482
B21: =_xlfn.XLOOKUP(TabelaAtivos[[#This Row],[Ambiente]],TabelaAmbientes[Ambiente],TabelaAmbientes[Cod_ambiente],"",0,1) | D21: =_xlfn.XLOOKUP(TabelaAtivos[[#This Row],[Ambiente]],TabelaAmbientes[Ambiente],TabelaAmbientes[Zona],"",0,1) | N21: =IF(M21="","",EDATE(M21,L21)) | O21: =IF(N21="","",YEAR(N21)) | P21: =IF(N21="","",TEXT(N21,"mmm")) | R21: =IF(OR(J21="",Q21=""),"",J21*Q21) | U21: =IF(N21="","Sem data",IF(N21<TODAY(),"Vencido",IF(N21<=TODAY()+30,"Próx. 30 dias",IF(N21<=TODAY()+90,"Próx. 90 dias","Programado")))) -> Sem data | X21: 51482
B22: =_xlfn.XLOOKUP(TabelaAtivos[[#This Row],[Ambiente]],TabelaAmbientes[Ambiente],TabelaAmbientes[Cod_ambiente],"",0,1) | D22: =_xlfn.XLOOKUP(TabelaAtivos[[#This Row],[Ambiente]],TabelaAmbientes[Ambiente],TabelaAmbientes[Zona],"",0,1) | N22: =IF(M22="","",EDATE(M22,L22)) | O22: =IF(N22="","",YEAR(N22)) | P22: =IF(N22="","",TEXT(N22,"mmm")) | R22: =IF(OR(J22="",Q22=""),"",J22*Q22) | U22: =IF(N22="","Sem data",IF(N22<TODAY(),"Vencido",IF(N22<=TODAY()+30,"Próx. 30 dias",IF(N22<=TODAY()+90,"Próx. 90 dias","Programado")))) -> Sem data | X22: 51482
B23: =_xlfn.XLOOKUP(TabelaAtivos[[#This Row],[Ambiente]],TabelaAmbientes[Ambiente],TabelaAmbientes[Cod_ambiente],"",0,1) | D23: =_xlfn.XLOOKUP(TabelaAtivos[[#This Row],[Ambiente]],TabelaAmbientes[Ambiente],TabelaAmbientes[Zona],"",0,1) | N23: =IF(M23="","",EDATE(M23,L23)) | O23: =IF(N23="","",YEAR(N23)) | P23: =IF(N23="","",TEXT(N23,"mmm")) | R23: =IF(OR(J23="",Q23=""),"",J23*Q23) | U23: =IF(N23="","Sem data",IF(N23<TODAY(),"Vencido",IF(N23<=TODAY()+30,"Próx. 30 dias",IF(N23<=TODAY()+90,"Próx. 90 dias","Programado")))) -> Sem data | X23: 51482
B24: =_xlfn.XLOOKUP(TabelaAtivos[[#This Row],[Ambiente]],TabelaAmbientes[Ambiente],TabelaAmbientes[Cod_ambiente],"",0,1) | D24: =_xlfn.XLOOKUP(TabelaAtivos[[#This Row],[Ambiente]],TabelaAmbientes[Ambiente],TabelaAmbientes[Zona],"",0,1) | N24: =IF(M24="","",EDATE(M24,L24)) | O24: =IF(N24="","",YEAR(N24)) | P24: =IF(N24="","",TEXT(N24,"mmm")) | R24: =IF(OR(J24="",Q24=""),"",J24*Q24) | U24: =IF(N24="","Sem data",IF(N24<TODAY(),"Vencido",IF(N24<=TODAY()+30,"Próx. 30 dias",IF(N24<=TODAY()+90,"Próx. 90 dias","Programado")))) -> Sem data | X24: 51482
B25: =_xlfn.XLOOKUP(TabelaAtivos[[#This Row],[Ambiente]],TabelaAmbientes[Ambiente],TabelaAmbientes[Cod_ambiente],"",0,1) | D25: =_xlfn.XLOOKUP(TabelaAtivos[[#This Row],[Ambiente]],TabelaAmbientes[Ambiente],TabelaAmbientes[Zona],"",0,1) | N25: =IF(M25="","",EDATE(M25,L25)) | O25: =IF(N25="","",YEAR(N25)) | P25: =IF(N25="","",TEXT(N25,"mmm")) | R25: =IF(OR(J25="",Q25=""),"",J25*Q25) | U25: =IF(N25="","Sem data",IF(N25<TODAY(),"Vencido",IF(N25<=TODAY()+30,"Próx. 30 dias",IF(N25<=TODAY()+90,"Próx. 90 dias","Programado")))) -> Sem data | X25: 51482
B26: =_xlfn.XLOOKUP(TabelaAtivos[[#This Row],[Ambiente]],TabelaAmbientes[Ambiente],TabelaAmbientes[Cod_ambiente],"",0,1) | D26: =_xlfn.XLOOKUP(TabelaAtivos[[#This Row],[Ambiente]],TabelaAmbientes[Ambiente],TabelaAmbientes[Zona],"",0,1) | N26: =IF(M26="","",EDATE(M26,L26)) | O26: =IF(N26="","",YEAR(N26)) | P26: =IF(N26="","",TEXT(N26,"mmm")) | R26: =IF(OR(J26="",Q26=""),"",J26*Q26) | U26: =IF(N26="","Sem data",IF(N26<TODAY(),"Vencido",IF(N26<=TODAY()+30,"Próx. 30 dias",IF(N26<=TODAY()+90,"Próx. 90 dias","Programado")))) -> Sem data | X26: 51482
B27: =_xlfn.XLOOKUP(TabelaAtivos[[#This Row],[Ambiente]],TabelaAmbientes[Ambiente],TabelaAmbientes[Cod_ambiente],"",0,1) | D27: =_xlfn.XLOOKUP(TabelaAtivos[[#This Row],[Ambiente]],TabelaAmbientes[Ambiente],TabelaAmbientes[Zona],"",0,1) | N27: =IF(M27="","",EDATE(M27,L27)) | O27: =IF(N27="","",YEAR(N27)) | P27: =IF(N27="","",TEXT(N27,"mmm")) | R27: =IF(OR(J27="",Q27=""),"",J27*Q27) | U27: =IF(N27="","Sem data",IF(N27<TODAY(),"Vencido",IF(N27<=TODAY()+30,"Próx. 30 dias",IF(N27<=TODAY()+90,"Próx. 90 dias","Programado")))) -> Sem data | X27: 51482
B28: =_xlfn.XLOOKUP(TabelaAtivos[[#This Row],[Ambiente]],TabelaAmbientes[Ambiente],TabelaAmbientes[Cod_ambiente],"",0,1) | D28: =_xlfn.XLOOKUP(TabelaAtivos[[#This Row],[Ambiente]],TabelaAmbientes[Ambiente],TabelaAmbientes[Zona],"",0,1) | N28: =IF(M28="","",EDATE(M28,L28)) | O28: =IF(N28="","",YEAR(N28)) | P28: =IF(N28="","",TEXT(N28,"mmm")) | R28: =IF(OR(J28="",Q28=""),"",J28*Q28) | U28: =IF(N28="","Sem data",IF(N28<TODAY(),"Vencido",IF(N28<=TODAY()+30,"Próx. 30 dias",IF(N28<=TODAY()+90,"Próx. 90 dias","Programado")))) -> Sem data | X28: 51482
B29: =_xlfn.XLOOKUP(TabelaAtivos[[#This Row],[Ambiente]],TabelaAmbientes[Ambiente],TabelaAmbientes[Cod_ambiente],"",0,1) | D29: =_xlfn.XLOOKUP(TabelaAtivos[[#This Row],[Ambiente]],TabelaAmbientes[Ambiente],TabelaAmbientes[Zona],"",0,1) | N29: =IF(M29="","",EDATE(M29,L29)) | O29: =IF(N29="","",YEAR(N29)) | P29: =IF(N29="","",TEXT(N29,"mmm")) | R29: =IF(OR(J29="",Q29=""),"",J29*Q29) | U29: =IF(N29="","Sem data",IF(N29<TODAY(),"Vencido",IF(N29<=TODAY()+30,"Próx. 30 dias",IF(N29<=TODAY()+90,"Próx. 90 dias","Programado")))) -> Sem data | X29: 51482
B30: =_xlfn.XLOOKUP(TabelaAtivos[[#This Row],[Ambiente]],TabelaAmbientes[Ambiente],TabelaAmbientes[Cod_ambiente],"",0,1) | D30: =_xlfn.XLOOKUP(TabelaAtivos[[#This Row],[Ambiente]],TabelaAmbientes[Ambiente],TabelaAmbientes[Zona],"",0,1) | N30: =IF(M30="","",EDATE(M30,L30)) | O30: =IF(N30="","",YEAR(N30)) | P30: =IF(N30="","",TEXT(N30,"mmm")) | R30: =IF(OR(J30="",Q30=""),"",J30*Q30) | U30: =IF(N30="","Sem data",IF(N30<TODAY(),"Vencido",IF(N30<=TODAY()+30,"Próx. 30 dias",IF(N30<=TODAY()+90,"Próx. 90 dias","Programado")))) -> Sem data | X30: 51482
B31: =_xlfn.XLOOKUP(TabelaAtivos[[#This Row],[Ambiente]],TabelaAmbientes[Ambiente],TabelaAmbientes[Cod_ambiente],"",0,1) | D31: =_xlfn.XLOOKUP(TabelaAtivos[[#This Row],[Ambiente]],TabelaAmbientes[Ambiente],TabelaAmbientes[Zona],"",0,1) | N31: =IF(M31="","",EDATE(M31,L31)) | O31: =IF(N31="","",YEAR(N31)) | P31: =IF(N31="","",TEXT(N31,"mmm")) | R31: =IF(OR(J31="",Q31=""),"",J31*Q31) | U31: =IF(N31="","Sem data",IF(N31<TODAY(),"Vencido",IF(N31<=TODAY()+30,"Próx. 30 dias",IF(N31<=TODAY()+90,"Próx. 90 dias","Programado")))) -> Sem data | X31: 51482
B32: =_xlfn.XLOOKUP(TabelaAtivos[[#This Row],[Ambiente]],TabelaAmbientes[Ambiente],TabelaAmbientes[Cod_ambiente],"",0,1) | D32: =_xlfn.XLOOKUP(TabelaAtivos[[#This Row],[Ambiente]],TabelaAmbientes[Ambiente],TabelaAmbientes[Zona],"",0,1) | N32: =IF(M32="","",EDATE(M32,L32)) | O32: =IF(N32="","",YEAR(N32)) | P32: =IF(N32="","",TEXT(N32,"mmm")) | R32: =IF(OR(J32="",Q32=""),"",J32*Q32) | U32: =IF(N32="","Sem data",IF(N32<TODAY(),"Vencido",IF(N32<=TODAY()+30,"Próx. 30 dias",IF(N32<=TODAY()+90,"Próx. 90 dias","Programado")))) -> Sem data | X32: 51482
... B200: =_xlfn.XLOOKUP(TabelaAtivos[[#This Row],[Ambiente]],TabelaAmbientes[Ambiente],TabelaAmbientes[Cod_ambiente],"",0,1) | D200: =_xlfn.XLOOKUP(TabelaAtivos[[#This Row],[Ambiente]],TabelaAmbientes[Ambiente],TabelaAmbientes[Zona],"",0,1) | N200: =IF(M200="","",EDATE(M200,L200)) | O200: =IF(N200="","",YEAR(N200)) | P200: =IF(N200="","",TEXT(N200,"mmm")) | R200: =IF(OR(J200="",Q200=""),"",J200*Q200) | U200: =IF(N200="","Sem data",IF(N200<TODAY(),"Vencido",IF(N200<=TODAY()+30,"Próx. 30 dias",IF(N200<=TODAY()+90,"Próx. 90 dias","Programado")))) -> Sem data | X200: 51482

Sheet Ambientes
A1: Cod_ambiente | B1: Ambiente | C1: Zona | D1: Observação | F1: Zonas
A2: S1 | B2: Suíte 1 | C2: Área íntima | F2: Área íntima
A3: S1B | B3: Banheiro suíte 1 | C3: Área íntima | F3: Trabalho
A4: S2 | B4: Suíte 2 | C4: Área íntima | F4: Social
A5: S2B | B5: Banheiro suíte 2 | C5: Área íntima | F5: Serviço
A6: S3 | B6: Suíte 3 | C6: Área íntima | F6: publica
A7: S3B | B7: Banheiro suíte 3 | C7: Área íntima
A8: ESC1 | B8: Escritório 1 | C8: Trabalho
A9: ESC2 | B9: Escritório 2 | C9: Trabalho
A10: SALA | B10: Sala | C10: Social
A11: VAR | B11: Varanda | C11: Social
A12: LAV | B12: Lavabo | C12: Social
A13: COPA | B13: Copa/cozinha | C13: Serviço
A14: SERV | B14: Área de serviço | C14: Serviço
A15: DEP | B15: Suíte dependência | C15: Serviço
A16: OFC | B16: Oficina | C16: Serviço
A17: DEPB | B17: Banheiro dependência | C17: Serviço
A18: EXT | B18: Externo | C18: publica
A19: nao cadastrado

Sheet Sistemas
A1: Cod_sistema | B1: Sistema | C1: Subsistema
A2: HID | B2: Hidráulico | C2: Água fria | G2: {=_xlfn._xlws.FILTER(TabelaSistemas[Subsistema],TabelaSistemas[Sistema]=Ativos!E2,"")} -> Água fria
A3: HID | B3: Hidráulico | C3: Água quente | G3: Água quente
A4: ESG | B4: Esgoto | C4: Esgoto sanitário
A5: DRE | B5: Drenagem | C5: Ralos | G5: {=_xlfn._xlws.FILTER(TabelaSistemas[Subsistema],TabelaSistemas[Sistema]=Ativos!E5,"")} -> Split
A6: ELE | B6: Elétrico | C6: Quadro
A7: ELE | B7: Elétrico | C7: Tomadas | G7: {=_xlfn._xlws.FILTER(TabelaSistemas[Subsistema],TabelaSistemas[Sistema]=Ativos!E7,"")} -> Split
A8: ILU | B8: Iluminação | C8: Luminárias | G8: {=_xlfn._xlws.FILTER(TabelaSistemas[Subsistema],TabelaSistemas[Sistema]=Ativos!E8,"")} -> Split
A9: CLI | B9: Climatização | C9: Split
A10: GAS | B10: Gás | C10: Tubulação/ponto
A11: PIN | B11: Pintura | C11: Interna
A12: PIN | B12: Pintura | C12: Externa
A13: REV | B13: Revestimentos | C13: Piso
A14: REV | B14: Revestimentos | C14: Parede
A15: ESQ | B15: Esquadrias | C15: Portas
A16: ESQ | B16: Esquadrias | C16: Janelas
A17: MAR | B17: Marcenaria | C17: Armários
A18: SEG | B18: Segurança/acesso | C18: Fechaduras

Sheet Rotinas
A1: Sistema | B1: Ativo | C1: Componente | D1: Ação | E1: Periodicidade_meses | F1: Custo_referencia | G1: Responsável_sugerido
A2: Hidráulico | B2: Lavatório | C2: Torneira | D2: Inspeção / troca de reparo | E2: 12 | F2: 150 | G2: Encanador
A3: Esgoto | B3: Lavatório | C3: Sifão | D3: Limpeza / inspeção | E3: 12 | F3: 80 | G3: Encanador
A4: Hidráulico | B4: Bacia sanitária | C4: Caixa acoplada / válvula | D4: Inspeção / regulagem | E4: 12 | F4: 150 | G4: Encanador
A5: Hidráulico | B5: Chuveiro | C5: Registro / misturador | D5: Inspeção | E5: 12 | F5: 120 | G5: Encanador
A6: Drenagem | B6: Ralo | C6: Ralo / grelha | D6: Limpeza | E6: 6 | F6: 80 | G6: Encanador
A7: Elétrico | B7: Quadro | C7: Disjuntores | D7: Inspeção | E7: 24 | F7: 250 | G7: Eletricista
A8: Elétrico | B8: Tomadas | C8: Conjunto de tomadas | D8: Inspeção | E8: 24 | F8: 100 | G8: Eletricista
A9: Iluminação | B9: Luminária | C9: Lâmpadas / drivers | D9: Revisão / troca | E9: 24 | F9: 120 | G9: Eletricista
A10: Climatização | B10: Ar-condicionado | C10: Evaporadora / condensadora | D10: Limpeza preventiva | E10: 6 | F10: 180 | G10: Técnico de ar-condicionado
A11: Gás | B11: Ponto de gás | C11: Mangueira / registro | D11: Inspeção / troca preventiva | E11: 12 | F11: 180 | G11: Técnico de gás
A12: Pintura | B12: Paredes internas | C12: Pintura | D12: Repintura | E12: 48 | F12: 2500 | G12: Pintor
A13: Revestimentos | B13: Piso | C13: Rejunte | D13: Inspeção / recomposição | E13: 36 | F13: 600 | G13: Pedreiro
... A16: Segurança/acesso | B16: Fechadura | C16: Fechadura / maçaneta | D16: Lubrificação / regulagem | E16: 12 | F16: 80 | G16: Chaveiro

Sheet Cronograma
A1: ID | B1: Próxima_manut | C1: Ano | D1: Mês | E1: Ambiente | F1: Sistema | G1: Ativo | H1: Ação_prevista | I1: Prioridade | J1: Status | K1: Custo_total_estimado
A2: =Ativos!A2 -> HID-S2B-001 | B2: =Ativos!N2 -> 46032 | C2: =Ativos!O2 -> 2026 | D2: =Ativos!P2 -> jan | E2: =Ativos!C2 -> Banheiro suíte 2 | F2: =Ativos!E2 -> Hidráulico | G2: =Ativos!G2 -> Lavatório | H2: =Ativos!I2 -> Inspeção / troca de reparo | I2: =Ativos!S2 -> Média | J2: =Ativos!U2 -> Vencido | K2: =Ativos!R2 -> 150
A3: =Ativos!A3 -> ESG-S2B-001 | B3: =Ativos!N3 -> 46032 | C3: =Ativos!O3 -> 2026 | D3: =Ativos!P3 -> jan | E3: =Ativos!C3 -> Banheiro suíte 2 | F3: =Ativos!E3 -> Esgoto | G3: =Ativos!G3 -> Lavatório | H3: =Ativos!I3 -> Limpeza / inspeção | I3: =Ativos!S3 -> Baixa | J3: =Ativos!U3 -> Vencido | K3: =Ativos!R3 -> 80
A4: =Ativos!A4 -> HID-S2B-002 | B4: =Ativos!N4 -> 46032 | C4: =Ativos!O4 -> 2026 | D4: =Ativos!P4 -> jan | E4: =Ativos!C4 -> Banheiro suíte 2 | F4: =Ativos!E4 -> Hidráulico | G4: =Ativos!G4 -> Bacia sanitária | H4: =Ativos!I4 -> Inspeção / regulagem | I4: =Ativos!S4 -> Média | J4: =Ativos!U4 -> Vencido | K4: =Ativos!R4 -> 150
A5: =Ativos!A5 -> CLI-SALA-001 | B5: =Ativos!N5 -> 45848 | C5: =Ativos!O5 -> 2025 | D5: =Ativos!P5 -> jul | E5: =Ativos!C5 -> Sala | F5: =Ativos!E5 -> Climatização | G5: =Ativos!G5 -> Ar-condicionado | H5: =Ativos!I5 -> Limpeza preventiva | I5: =Ativos!S5 -> Alta | J5: =Ativos!U5 -> Vencido | K5: =Ativos!R5 -> 180
A6: =Ativos!A6 -> CLI-S1-001 | B6: =Ativos!N6 -> 45848 | C6: =Ativos!O6 -> 2025 | D6: =Ativos!P6 -> jul | E6: =Ativos!C6 -> Suíte 1 | F6: =Ativos!E6 -> Climatização | G6: =Ativos!G6 -> Ar-condicionado | H6: =Ativos!I6 -> Limpeza preventiva | I6: =Ativos!S6 -> Alta | J6: =Ativos!U6 -> Vencido | K6: =Ativos!R6 -> 180
A7: =Ativos!A7 -> CLI-S2-001 | B7: =Ativos!N7 -> 45848 | C7: =Ativos!O7 -> 2025 | D7: =Ativos!P7 -> jul | E7: =Ativos!C7 -> Suíte 2 | F7: =Ativos!E7 -> Climatização | G7: =Ativos!G7 -> Ar-condicionado | H7: =Ativos!I7 -> Limpeza preventiva | I7: =Ativos!S7 -> Alta | J7: =Ativos!U7 -> Vencido | K7: =Ativos!R7 -> 180
A8: =Ativos!A8 -> CLI-S3-001 | B8: =Ativos!N8 -> 45848 | C8: =Ativos!O8 -> 2025 | D8: =Ativos!P8 -> jul | E8: =Ativos!C8 -> Suíte 3 | F8: =Ativos!E8 -> Climatização | G8: =Ativos!G8 -> Ar-condicionado | H8: =Ativos!I8 -> Limpeza preventiva | I8: =Ativos!S8 -> Alta | J8: =Ativos!U8 -> Vencido | K8: =Ativos!R8 -> 180
A9: =Ativos!A9 -> ELE-APT-001 | B9: =Ativos!N9 -> 46397 | C9: =Ativos!O9 -> 2027 | D9: =Ativos!P9 -> jan | E9: =Ativos!C9 -> Sala | F9: =Ativos!E9 -> Elétrico | G9: =Ativos!G9 -> Quadro elétrico | H9: =Ativos!I9 -> Inspeção | I9: =Ativos!S9 -> Média | J9: =Ativos!U9 -> Programado | K9: =Ativos!R9 -> 20000
A10: =Ativos!A10 -> ELE-ESC1-001 | B10: =Ativos!N10 -> 46397 | C10: =Ativos!O10 -> 2027 | D10: =Ativos!P10 -> jan | E10: =Ativos!C10 -> Escritório 1 | F10: =Ativos!E10 -> Elétrico | G10: =Ativos!G10 -> Tomadas gerais | H10: =Ativos!I10 -> Inspeção | I10: =Ativos!S10 -> Baixa | J10: =Ativos!U10 -> Programado | K10: =Ativos!R10 -> 100
A11: =Ativos!A11 -> GAS-COPA-001 | B11: =Ativos!N11 -> 46032 | C11: =Ativos!O11 -> 2026 | D11: =Ativos!P11 -> jan | E11: =Ativos!C11 -> Copa/cozinha | F11: =Ativos!E11 -> Gás | G11: =Ativos!G11 -> Ponto de gás | H11: =Ativos!I11 -> Inspeção / troca preventiva | I11: =Ativos!S11 -> Alta | J11: =Ativos!U11 -> Vencido | K11: =Ativos!R11 -> 180
A12: =Ativos!A12 -> PIN-SALA-001 | B12: =Ativos!N12 -> 46762 | C12: =Ativos!O12 -> 2028 | D12: =Ativos!P12 -> jan | E12: =Ativos!C12 -> Sala | F12: =Ativos!E12 -> Pintura | G12: =Ativos!G12 -> Paredes internas | H12: =Ativos!I12 -> Repintura | I12: =Ativos!S12 -> Média | J12: =Ativos!U12 -> Programado | K12: =Ativos!R12 -> 2500
A13: =Ativos!A13 -> REV-VAR-001 | B13: =Ativos!N13 -> 46397 | C13: =Ativos!O13 -> 2027 | D13: =Ativos!P13 -> jan | E13: =Ativos!C13 -> Varanda | F13: =Ativos!E13 -> Revestimentos | G13: =Ativos!G13 -> Piso | H13: =Ativos!I13 -> Inspeção / recomposição | I13: =Ativos!S13 -> Média | J13: =Ativos!U13 -> Programado | K13: =Ativos!R13 -> 600
... A200: =Ativos!A200 -> 0 | B200: =Ativos!N200 | C200: =Ativos!O200 | D200: =Ativos!P200 | E200: =Ativos!C200 -> 0 | F200: =Ativos!E200 -> 0 | G200: =Ativos!G200 -> 0 | H200: =Ativos!I200 -> 0 | I200: =Ativos!S200 -> 0 | J200: =Ativos!U200 -> Sem data | K200: =Ativos!R200

Sheet Listas
A1: Prioridade | C1: Estado | E1: Unidade | G1: Sistema | I1: Ambiente | K1: Status
A2: Baixa | C2: Bom | E2: un | G2: {=_xlfn._xlws.SORT(_xlfn.UNIQUE(_xlfn._xlws.FILTER(TabelaSistemas[Sistema],TabelaSistemas[Sistema]<>"")))} -> Climatização | I2: {=_xlfn._xlws.SORT(_xlfn.UNIQUE(_xlfn._xlws.FILTER(TabelaAmbientes[Ambiente],TabelaAmbientes[Ambiente]<>"")))} -> Área de serviço | K2: Vencido
A3: Média | C3: Regular | E3: cj | G3: Drenagem | I3: Banheiro dependência | K3: Próx. 30 dias
A4: Alta | C4: Ruim | E4: serv | G4: Elétrico | I4: Banheiro suíte 1 | K4: Próx. 90 dias
A5: Crítica | C5: Desconhecido | E5: m² | G5: Esgoto | I5: Banheiro suíte 2 | K5: Programado
E6: m | G6: Esquadrias | I6: Banheiro suíte 3 | K6: Sem data
E7: ponto | G7: Gás | I7: Copa/cozinha
G8: Hidráulico | I8: Escritório 1
G9: Iluminação | I9: Escritório 2
G10: Marcenaria | I10: Externo
G11: Pintura | I11: Lavabo
G12: Revestimentos | I12: Oficina
G13: Segurança/acesso | I13: Sala
I14: Suíte 1
I15: Suíte 2
I16: Suíte 3
I17: Suíte dependência
I18: Varanda
